nia_web_eval_agent-1.3.0.dist-info/licenses/LICENSE
webEvalAgent/__init__.py
webEvalAgent/mcp_server.py
webEvalAgent/src/__init__.py
webEvalAgent/src/agent_overlay.js
webEvalAgent/src/api_utils.py
webEvalAgent/src/browser_manager.py
webEvalAgent/src/browser_utils.py
webEvalAgent/src/env_utils.py
webEvalAgent/src/log_server.py
webEvalAgent/src/prompts.py
webEvalAgent/src/tool_handlers.py
webEvalAgent/src/utils.py
webEvalAgent/src/__pycache__/__init__.cpython-312.pyc
webEvalAgent/src/__pycache__/api_utils.cpython-312.pyc
webEvalAgent/src/__pycache__/browser_manager.cpython-312.pyc
webEvalAgent/src/__pycache__/browser_utils.cpython-312.pyc
webEvalAgent/src/__pycache__/env_utils.cpython-312.pyc
webEvalAgent/src/__pycache__/log_server.cpython-312.pyc
webEvalAgent/src/__pycache__/prompts.cpython-312.pyc
webEvalAgent/src/__pycache__/tool_handlers.cpython-312.pyc
webEvalAgent/src/__pycache__/utils.cpython-312.pyc
webEvalAgent/templates/static/index.html
nia_web_eval_agent-1.3.0.dist-info/METADATA
nia_web_eval_agent-1.3.0.dist-info/WHEEL
nia_web_eval_agent-1.3.0.dist-info/entry_points.txt
nia_web_eval_agent-1.3.0.dist-info/top_level.txt
nia_web_eval_agent-1.3.0.dist-info/RECORD
