Metadata-Version: 2.4
Name: nia-web-eval-agent
Version: 1.3.0
Summary: NIA AI - Web Evaluation Agent for browser testing and UX analysis
Author-email: NIA AI Team <team@trynia.ai>
License-Expression: MIT
Project-URL: Homepage, https://trynia.ai
Project-URL: Documentation, https://trynia.ai/docs/web-eval-agent
Project-URL: Source, https://github.com/nia-ai-app/web-eval-agent
Project-URL: Bug Tracker, https://github.com/nia-ai-app/web-eval-agent/issues
Keywords: mcp,web-testing,browser-automation,ux-testing,ai
Classifier: Development Status :: 4 - Beta
Classifier: Intended Audience :: Developers
Classifier: Programming Language :: Python :: 3
Classifier: Programming Language :: Python :: 3.11
Classifier: Programming Language :: Python :: 3.12
Requires-Python: >=3.11
License-File: LICENSE
Requires-Dist: browser-use==0.1.40
Requires-Dist: google-genai>=1.7.0
Requires-Dist: google-generativeai>=0.8.4
Requires-Dist: langchain>=0.3.21
Requires-Dist: langchain-anthropic>=0.3.3
Requires-Dist: langchain-google-genai>=2.0.10
Requires-Dist: mcp>=1.6.0
Requires-Dist: python-dotenv>=1.1.0
Requires-Dist: playwright>=1.41.0
Requires-Dist: flask>=3.1.0
Requires-Dist: flask-socketio>=5.5.1
Requires-Dist: httpx>=0.28.0
Provides-Extra: dev
Requires-Dist: ruff>=0.11.9; extra == "dev"
Requires-Dist: build; extra == "dev"
Requires-Dist: twine; extra == "dev"
Dynamic: license-file
